LICENSE
MANIFEST.in
README.md
requirements.txt
setup.py
canalplus/__init__.py
canalplus/__main__.py
canalplus/colored_logging.py
canalplus/mkstemp_ctx.py
canalplus/progress_display.py
canalplus.egg-info/PKG-INFO
canalplus.egg-info/SOURCES.txt
canalplus.egg-info/dependency_links.txt
canalplus.egg-info/entry_points.txt
canalplus.egg-info/requires.txt
canalplus.egg-info/top_level.txt
tests/__init__.py