Metadata-Version: 1.1
Name: canalplus
Version: 1.0.9
Summary: Parcourir/visionner/télécharger les vidéos mises en ligne par la chaine Canal+
Home-page: https://github.com/desbma/canalplus
Author: desbma
Author-email: UNKNOWN
License: UNKNOWN
Download-URL: https://github.com/desbma/canalplus/archive/1.0.9.tar.gz
Keywords: canal+,canal,canalplus,video,vidéo,download,télécharger
Platform: UNKNOWN
Classifier: Development Status :: 5 - Production/Stable
Classifier: Environment :: Console
Classifier: Intended Audience :: Developers
Classifier: Intended Audience :: End Users/Desktop
Classifier: License :: OSI Approved :: GNU General Public License v3 (GPLv3)
Classifier: Natural Language :: English
Classifier: Natural Language :: French
Classifier: Operating System :: OS Independent
Classifier: Programming Language :: Python
Classifier: Programming Language :: Python :: 3
Classifier: Programming Language :: Python :: 3 :: Only
Classifier: Programming Language :: Python :: 3.3
Classifier: Programming Language :: Python :: 3.4
Classifier: Programming Language :: Python :: 3.5
Classifier: Topic :: Multimedia :: Video
Classifier: Topic :: Utilities
